sliceit/__init__.py
sliceit/_slice_view.py
sliceit-0.0.1.dist-info/LICENSE
sliceit-0.0.1.dist-info/METADATA
sliceit-0.0.1.dist-info/WHEEL
sliceit-0.0.1.dist-info/top_level.txt
sliceit-0.0.1.dist-info/RECORD
