Metadata-Version: 2.1
Name: sliceit
Version: 0.0.1
Summary: Dynamically sized slice views which avoid storing their own data.
Home-page: https://github.com/SimpleArt/sliceit
Author: Jack Nguyen
Author-email: jackyeenguyen@gmail.com
License: UNKNOWN
Platform: UNKNOWN
Classifier: Programming Language :: Python :: 3
Classifier: License :: OSI Approved :: MIT License
Classifier: Operating System :: OS Independent
Requires-Python: >=3.5
License-File: LICENSE
